MANIFEST.in
README.md
setup.py
./src/mrasyncmc/internals/city.c
./src/mrasyncmc/internals/memcachedclient.c
./src/mrasyncmc/internals/module.c
src/mrasyncmc/__init__.py
src/mrasyncmc/client.py
src/mrasyncmc/pool.py
src/mrasyncmc/server.py
src/mrasyncmc.egg-info/PKG-INFO
src/mrasyncmc.egg-info/SOURCES.txt
src/mrasyncmc.egg-info/dependency_links.txt
src/mrasyncmc.egg-info/top_level.txt
src/mrasyncmc.egg-info/zip-safe
src/mrasyncmc/delme/__init__.py
src/mrasyncmc/delme/client.py
src/mrasyncmc/delme/pool.py
src/mrasyncmc/delme/server.py
src/mrasyncmc/internals/city.c
src/mrasyncmc/internals/city.h
src/mrasyncmc/internals/citycrc.h
src/mrasyncmc/internals/common.h
src/mrasyncmc/internals/memcachedclient.c
src/mrasyncmc/internals/memcachedclient.h
src/mrasyncmc/internals/module.c
src/mrasyncmc/internals/module.h