Metadata-Version: 1.1
Name: mrasyncmc
Version: 1.0.0
Summary: Python asyncio memcached client
Home-page: https://github.com/MarkReedZ/mrasyncmc
Author: Mark Reed
Author-email: mark@untilfluent.com
License: MIT License
Platform: UNKNOWN
Classifier: Intended Audience :: Developers
Classifier: Programming Language :: Python
Classifier: Programming Language :: Python :: 3
Classifier: Programming Language :: Python :: 3.5
Classifier: Programming Language :: Python :: 3.6
